<?xml version="1.0"?>
<network xmlns="http://sndlib.zib.de/network" version="1.0">
 <meta>
  <granularity>5min</granularity>
  <time>20040311-0055</time>
  <unit>MBITPERSEC</unit>
  <origin>Yin Zhang, http://userweb.cs.utexas.edu/~yzhang/research/AbileneTM/</origin>
 </meta>
 <networkStructure>
  <nodes coordinatesType="geographical">
   <node id="ATLAM5">
    <coordinates>
     <x>-84.383300</x>
     <y>33.750000</y>
    </coordinates>
   </node>
   <node id="ATLAng">
    <coordinates>
     <x>-85.5</x>
     <y>34.5</y>
    </coordinates>
   </node>
   <node id="CHINng">
    <coordinates>
     <x>-87.616700</x>
     <y>41.833300</y>
    </coordinates>
   </node>
   <node id="DNVRng">
    <coordinates>
     <x>-105.000000</x>
     <y>40.750000</y>
    </coordinates>
   </node>
   <node id="HSTNng">
    <coordinates>
     <x>-95.517364</x>
     <y>29.770031</y>
    </coordinates>
   </node>
   <node id="IPLSng">
    <coordinates>
     <x>-86.159535</x>
     <y>39.780622</y>
    </coordinates>
   </node>
   <node id="KSCYng">
    <coordinates>
     <x>-96.596704</x>
     <y>38.961694</y>
    </coordinates>
   </node>
   <node id="LOSAng">
    <coordinates>
     <x>-118.250000</x>
     <y>34.050000</y>
    </coordinates>
   </node>
   <node id="NYCMng">
    <coordinates>
     <x>-73.966700</x>
     <y>40.783300</y>
    </coordinates>
   </node>
   <node id="SNVAng">
    <coordinates>
     <x>-122.02553</x>
     <y>37.38575</y>
    </coordinates>
   </node>
   <node id="STTLng">
    <coordinates>
     <x>-122.300000</x>
     <y>47.600000</y>
    </coordinates>
   </node>
   <node id="WASHng">
    <coordinates>
     <x>-77.026842</x>
     <y>38.897303</y>
    </coordinates>
   </node>
  </nodes>
  <links>
  </links>
 </networkStructure>
 <demands>
  <demand id="ATLAM5_ATLAng">
   <source>ATLAM5</source>
   <target>ATLAng</target>
   <demandValue> 0.353400 </demandValue>
  </demand>
  <demand id="ATLAM5_CHINng">
   <source>ATLAM5</source>
   <target>CHINng</target>
   <demandValue> 1.599339 </demandValue>
  </demand>
  <demand id="ATLAM5_DNVRng">
   <source>ATLAM5</source>
   <target>DNVRng</target>
   <demandValue> 0.026667 </demandValue>
  </demand>
  <demand id="ATLAM5_HSTNng">
   <source>ATLAM5</source>
   <target>HSTNng</target>
   <demandValue> 0.056123 </demandValue>
  </demand>
  <demand id="ATLAM5_IPLSng">
   <source>ATLAM5</source>
   <target>IPLSng</target>
   <demandValue> 0.562363 </demandValue>
  </demand>
  <demand id="ATLAM5_KSCYng">
   <source>ATLAM5</source>
   <target>KSCYng</target>
   <demandValue> 0.089376 </demandValue>
  </demand>
  <demand id="ATLAM5_LOSAng">
   <source>ATLAM5</source>
   <target>LOSAng</target>
   <demandValue> 1.135011 </demandValue>
  </demand>
  <demand id="ATLAM5_NYCMng">
   <source>ATLAM5</source>
   <target>NYCMng</target>
   <demandValue> 0.858565 </demandValue>
  </demand>
  <demand id="ATLAM5_STTLng">
   <source>ATLAM5</source>
   <target>STTLng</target>
   <demandValue> 0.084501 </demandValue>
  </demand>
  <demand id="ATLAM5_WASHng">
   <source>ATLAM5</source>
   <target>WASHng</target>
   <demandValue> 0.821965 </demandValue>
  </demand>
  <demand id="ATLAng_ATLAM5">
   <source>ATLAng</source>
   <target>ATLAM5</target>
   <demandValue> 0.199101 </demandValue>
  </demand>
  <demand id="ATLAng_CHINng">
   <source>ATLAng</source>
   <target>CHINng</target>
   <demandValue> 23.866256 </demandValue>
  </demand>
  <demand id="ATLAng_DNVRng">
   <source>ATLAng</source>
   <target>DNVRng</target>
   <demandValue> 6.000163 </demandValue>
  </demand>
  <demand id="ATLAng_HSTNng">
   <source>ATLAng</source>
   <target>HSTNng</target>
   <demandValue> 3.991069 </demandValue>
  </demand>
  <demand id="ATLAng_IPLSng">
   <source>ATLAng</source>
   <target>IPLSng</target>
   <demandValue> 22.447744 </demandValue>
  </demand>
  <demand id="ATLAng_KSCYng">
   <source>ATLAng</source>
   <target>KSCYng</target>
   <demandValue> 4.500371 </demandValue>
  </demand>
  <demand id="ATLAng_LOSAng">
   <source>ATLAng</source>
   <target>LOSAng</target>
   <demandValue> 20.883976 </demandValue>
  </demand>
  <demand id="ATLAng_NYCMng">
   <source>ATLAng</source>
   <target>NYCMng</target>
   <demandValue> 14.037259 </demandValue>
  </demand>
  <demand id="ATLAng_SNVAng">
   <source>ATLAng</source>
   <target>SNVAng</target>
   <demandValue> 4.084069 </demandValue>
  </demand>
  <demand id="ATLAng_STTLng">
   <source>ATLAng</source>
   <target>STTLng</target>
   <demandValue> 7.814085 </demandValue>
  </demand>
  <demand id="ATLAng_WASHng">
   <source>ATLAng</source>
   <target>WASHng</target>
   <demandValue> 44.759880 </demandValue>
  </demand>
  <demand id="CHINng_ATLAM5">
   <source>CHINng</source>
   <target>ATLAM5</target>
   <demandValue> 1.204901 </demandValue>
  </demand>
  <demand id="CHINng_ATLAng">
   <source>CHINng</source>
   <target>ATLAng</target>
   <demandValue> 20.039200 </demandValue>
  </demand>
  <demand id="CHINng_DNVRng">
   <source>CHINng</source>
   <target>DNVRng</target>
   <demandValue> 15.460195 </demandValue>
  </demand>
  <demand id="CHINng_HSTNng">
   <source>CHINng</source>
   <target>HSTNng</target>
   <demandValue> 34.667328 </demandValue>
  </demand>
  <demand id="CHINng_IPLSng">
   <source>CHINng</source>
   <target>IPLSng</target>
   <demandValue> 61.938421 </demandValue>
  </demand>
  <demand id="CHINng_KSCYng">
   <source>CHINng</source>
   <target>KSCYng</target>
   <demandValue> 35.351643 </demandValue>
  </demand>
  <demand id="CHINng_LOSAng">
   <source>CHINng</source>
   <target>LOSAng</target>
   <demandValue> 76.468864 </demandValue>
  </demand>
  <demand id="CHINng_NYCMng">
   <source>CHINng</source>
   <target>NYCMng</target>
   <demandValue> 25.502128 </demandValue>
  </demand>
  <demand id="CHINng_SNVAng">
   <source>CHINng</source>
   <target>SNVAng</target>
   <demandValue> 8.802632 </demandValue>
  </demand>
  <demand id="CHINng_STTLng">
   <source>CHINng</source>
   <target>STTLng</target>
   <demandValue> 22.608419 </demandValue>
  </demand>
  <demand id="CHINng_WASHng">
   <source>CHINng</source>
   <target>WASHng</target>
   <demandValue> 33.031211 </demandValue>
  </demand>
  <demand id="DNVRng_ATLAM5">
   <source>DNVRng</source>
   <target>ATLAM5</target>
   <demandValue> 0.164549 </demandValue>
  </demand>
  <demand id="DNVRng_ATLAng">
   <source>DNVRng</source>
   <target>ATLAng</target>
   <demandValue> 6.258813 </demandValue>
  </demand>
  <demand id="DNVRng_CHINng">
   <source>DNVRng</source>
   <target>CHINng</target>
   <demandValue> 65.810912 </demandValue>
  </demand>
  <demand id="DNVRng_HSTNng">
   <source>DNVRng</source>
   <target>HSTNng</target>
   <demandValue> 21.136459 </demandValue>
  </demand>
  <demand id="DNVRng_IPLSng">
   <source>DNVRng</source>
   <target>IPLSng</target>
   <demandValue> 35.534059 </demandValue>
  </demand>
  <demand id="DNVRng_KSCYng">
   <source>DNVRng</source>
   <target>KSCYng</target>
   <demandValue> 10.925293 </demandValue>
  </demand>
  <demand id="DNVRng_LOSAng">
   <source>DNVRng</source>
   <target>LOSAng</target>
   <demandValue> 13.819067 </demandValue>
  </demand>
  <demand id="DNVRng_NYCMng">
   <source>DNVRng</source>
   <target>NYCMng</target>
   <demandValue> 18.150371 </demandValue>
  </demand>
  <demand id="DNVRng_SNVAng">
   <source>DNVRng</source>
   <target>SNVAng</target>
   <demandValue> 10.537259 </demandValue>
  </demand>
  <demand id="DNVRng_STTLng">
   <source>DNVRng</source>
   <target>STTLng</target>
   <demandValue> 20.820741 </demandValue>
  </demand>
  <demand id="DNVRng_WASHng">
   <source>DNVRng</source>
   <target>WASHng</target>
   <demandValue> 54.494128 </demandValue>
  </demand>
  <demand id="HSTNng_ATLAM5">
   <source>HSTNng</source>
   <target>ATLAM5</target>
   <demandValue> 1.594637 </demandValue>
  </demand>
  <demand id="HSTNng_ATLAng">
   <source>HSTNng</source>
   <target>ATLAng</target>
   <demandValue> 4.986456 </demandValue>
  </demand>
  <demand id="HSTNng_CHINng">
   <source>HSTNng</source>
   <target>CHINng</target>
   <demandValue> 34.741336 </demandValue>
  </demand>
  <demand id="HSTNng_DNVRng">
   <source>HSTNng</source>
   <target>DNVRng</target>
   <demandValue> 6.009693 </demandValue>
  </demand>
  <demand id="HSTNng_IPLSng">
   <source>HSTNng</source>
   <target>IPLSng</target>
   <demandValue> 11.644869 </demandValue>
  </demand>
  <demand id="HSTNng_KSCYng">
   <source>HSTNng</source>
   <target>KSCYng</target>
   <demandValue> 5.352493 </demandValue>
  </demand>
  <demand id="HSTNng_LOSAng">
   <source>HSTNng</source>
   <target>LOSAng</target>
   <demandValue> 9.657749 </demandValue>
  </demand>
  <demand id="HSTNng_NYCMng">
   <source>HSTNng</source>
   <target>NYCMng</target>
   <demandValue> 7.761992 </demandValue>
  </demand>
  <demand id="HSTNng_SNVAng">
   <source>HSTNng</source>
   <target>SNVAng</target>
   <demandValue> 2.553987 </demandValue>
  </demand>
  <demand id="HSTNng_STTLng">
   <source>HSTNng</source>
   <target>STTLng</target>
   <demandValue> 2.610139 </demandValue>
  </demand>
  <demand id="HSTNng_WASHng">
   <source>HSTNng</source>
   <target>WASHng</target>
   <demandValue> 4.951989 </demandValue>
  </demand>
  <demand id="IPLSng_ATLAM5">
   <source>IPLSng</source>
   <target>ATLAM5</target>
   <demandValue> 0.309285 </demandValue>
  </demand>
  <demand id="IPLSng_ATLAng">
   <source>IPLSng</source>
   <target>ATLAng</target>
   <demandValue> 15.339059 </demandValue>
  </demand>
  <demand id="IPLSng_CHINng">
   <source>IPLSng</source>
   <target>CHINng</target>
   <demandValue> 115.376888 </demandValue>
  </demand>
  <demand id="IPLSng_DNVRng">
   <source>IPLSng</source>
   <target>DNVRng</target>
   <demandValue> 20.903221 </demandValue>
  </demand>
  <demand id="IPLSng_HSTNng">
   <source>IPLSng</source>
   <target>HSTNng</target>
   <demandValue> 10.448232 </demandValue>
  </demand>
  <demand id="IPLSng_KSCYng">
   <source>IPLSng</source>
   <target>KSCYng</target>
   <demandValue> 14.840267 </demandValue>
  </demand>
  <demand id="IPLSng_LOSAng">
   <source>IPLSng</source>
   <target>LOSAng</target>
   <demandValue> 33.918112 </demandValue>
  </demand>
  <demand id="IPLSng_NYCMng">
   <source>IPLSng</source>
   <target>NYCMng</target>
   <demandValue> 30.522160 </demandValue>
  </demand>
  <demand id="IPLSng_SNVAng">
   <source>IPLSng</source>
   <target>SNVAng</target>
   <demandValue> 3.378763 </demandValue>
  </demand>
  <demand id="IPLSng_STTLng">
   <source>IPLSng</source>
   <target>STTLng</target>
   <demandValue> 19.064864 </demandValue>
  </demand>
  <demand id="IPLSng_WASHng">
   <source>IPLSng</source>
   <target>WASHng</target>
   <demandValue> 17.955947 </demandValue>
  </demand>
  <demand id="KSCYng_ATLAM5">
   <source>KSCYng</source>
   <target>ATLAM5</target>
   <demandValue> 0.135648 </demandValue>
  </demand>
  <demand id="KSCYng_ATLAng">
   <source>KSCYng</source>
   <target>ATLAng</target>
   <demandValue> 3.340587 </demandValue>
  </demand>
  <demand id="KSCYng_CHINng">
   <source>KSCYng</source>
   <target>CHINng</target>
   <demandValue> 37.541877 </demandValue>
  </demand>
  <demand id="KSCYng_DNVRng">
   <source>KSCYng</source>
   <target>DNVRng</target>
   <demandValue> 11.758947 </demandValue>
  </demand>
  <demand id="KSCYng_HSTNng">
   <source>KSCYng</source>
   <target>HSTNng</target>
   <demandValue> 4.895643 </demandValue>
  </demand>
  <demand id="KSCYng_IPLSng">
   <source>KSCYng</source>
   <target>IPLSng</target>
   <demandValue> 11.376453 </demandValue>
  </demand>
  <demand id="KSCYng_LOSAng">
   <source>KSCYng</source>
   <target>LOSAng</target>
   <demandValue> 10.597488 </demandValue>
  </demand>
  <demand id="KSCYng_NYCMng">
   <source>KSCYng</source>
   <target>NYCMng</target>
   <demandValue> 11.655240 </demandValue>
  </demand>
  <demand id="KSCYng_SNVAng">
   <source>KSCYng</source>
   <target>SNVAng</target>
   <demandValue> 3.748317 </demandValue>
  </demand>
  <demand id="KSCYng_STTLng">
   <source>KSCYng</source>
   <target>STTLng</target>
   <demandValue> 3.857123 </demandValue>
  </demand>
  <demand id="KSCYng_WASHng">
   <source>KSCYng</source>
   <target>WASHng</target>
   <demandValue> 10.921261 </demandValue>
  </demand>
  <demand id="LOSAng_ATLAM5">
   <source>LOSAng</source>
   <target>ATLAM5</target>
   <demandValue> 1.586045 </demandValue>
  </demand>
  <demand id="LOSAng_ATLAng">
   <source>LOSAng</source>
   <target>ATLAng</target>
   <demandValue> 21.783192 </demandValue>
  </demand>
  <demand id="LOSAng_CHINng">
   <source>LOSAng</source>
   <target>CHINng</target>
   <demandValue> 134.779032 </demandValue>
  </demand>
  <demand id="LOSAng_DNVRng">
   <source>LOSAng</source>
   <target>DNVRng</target>
   <demandValue> 14.033304 </demandValue>
  </demand>
  <demand id="LOSAng_HSTNng">
   <source>LOSAng</source>
   <target>HSTNng</target>
   <demandValue> 12.470989 </demandValue>
  </demand>
  <demand id="LOSAng_IPLSng">
   <source>LOSAng</source>
   <target>IPLSng</target>
   <demandValue> 39.810024 </demandValue>
  </demand>
  <demand id="LOSAng_KSCYng">
   <source>LOSAng</source>
   <target>KSCYng</target>
   <demandValue> 10.620821 </demandValue>
  </demand>
  <demand id="LOSAng_NYCMng">
   <source>LOSAng</source>
   <target>NYCMng</target>
   <demandValue> 65.904131 </demandValue>
  </demand>
  <demand id="LOSAng_SNVAng">
   <source>LOSAng</source>
   <target>SNVAng</target>
   <demandValue> 11.268315 </demandValue>
  </demand>
  <demand id="LOSAng_STTLng">
   <source>LOSAng</source>
   <target>STTLng</target>
   <demandValue> 35.626403 </demandValue>
  </demand>
  <demand id="LOSAng_WASHng">
   <source>LOSAng</source>
   <target>WASHng</target>
   <demandValue> 77.619320 </demandValue>
  </demand>
  <demand id="NYCMng_ATLAM5">
   <source>NYCMng</source>
   <target>ATLAM5</target>
   <demandValue> 1.836997 </demandValue>
  </demand>
  <demand id="NYCMng_ATLAng">
   <source>NYCMng</source>
   <target>ATLAng</target>
   <demandValue> 29.176037 </demandValue>
  </demand>
  <demand id="NYCMng_CHINng">
   <source>NYCMng</source>
   <target>CHINng</target>
   <demandValue> 88.050067 </demandValue>
  </demand>
  <demand id="NYCMng_DNVRng">
   <source>NYCMng</source>
   <target>DNVRng</target>
   <demandValue> 42.220872 </demandValue>
  </demand>
  <demand id="NYCMng_HSTNng">
   <source>NYCMng</source>
   <target>HSTNng</target>
   <demandValue> 28.898355 </demandValue>
  </demand>
  <demand id="NYCMng_IPLSng">
   <source>NYCMng</source>
   <target>IPLSng</target>
   <demandValue> 50.110040 </demandValue>
  </demand>
  <demand id="NYCMng_KSCYng">
   <source>NYCMng</source>
   <target>KSCYng</target>
   <demandValue> 40.790419 </demandValue>
  </demand>
  <demand id="NYCMng_LOSAng">
   <source>NYCMng</source>
   <target>LOSAng</target>
   <demandValue> 97.456285 </demandValue>
  </demand>
  <demand id="NYCMng_SNVAng">
   <source>NYCMng</source>
   <target>SNVAng</target>
   <demandValue> 20.241048 </demandValue>
  </demand>
  <demand id="NYCMng_STTLng">
   <source>NYCMng</source>
   <target>STTLng</target>
   <demandValue> 45.717811 </demandValue>
  </demand>
  <demand id="NYCMng_WASHng">
   <source>NYCMng</source>
   <target>WASHng</target>
   <demandValue> 115.928600 </demandValue>
  </demand>
  <demand id="SNVAng_ATLAng">
   <source>SNVAng</source>
   <target>ATLAng</target>
   <demandValue> 1.193779 </demandValue>
  </demand>
  <demand id="SNVAng_CHINng">
   <source>SNVAng</source>
   <target>CHINng</target>
   <demandValue> 5.347768 </demandValue>
  </demand>
  <demand id="SNVAng_DNVRng">
   <source>SNVAng</source>
   <target>DNVRng</target>
   <demandValue> 10.840925 </demandValue>
  </demand>
  <demand id="SNVAng_HSTNng">
   <source>SNVAng</source>
   <target>HSTNng</target>
   <demandValue> 1.702389 </demandValue>
  </demand>
  <demand id="SNVAng_IPLSng">
   <source>SNVAng</source>
   <target>IPLSng</target>
   <demandValue> 2.270173 </demandValue>
  </demand>
  <demand id="SNVAng_KSCYng">
   <source>SNVAng</source>
   <target>KSCYng</target>
   <demandValue> 0.918088 </demandValue>
  </demand>
  <demand id="SNVAng_LOSAng">
   <source>SNVAng</source>
   <target>LOSAng</target>
   <demandValue> 43.551627 </demandValue>
  </demand>
  <demand id="SNVAng_NYCMng">
   <source>SNVAng</source>
   <target>NYCMng</target>
   <demandValue> 3.696944 </demandValue>
  </demand>
  <demand id="SNVAng_STTLng">
   <source>SNVAng</source>
   <target>STTLng</target>
   <demandValue> 53.017093 </demandValue>
  </demand>
  <demand id="SNVAng_WASHng">
   <source>SNVAng</source>
   <target>WASHng</target>
   <demandValue> 1.798749 </demandValue>
  </demand>
  <demand id="STTLng_ATLAM5">
   <source>STTLng</source>
   <target>ATLAM5</target>
   <demandValue> 2.001635 </demandValue>
  </demand>
  <demand id="STTLng_ATLAng">
   <source>STTLng</source>
   <target>ATLAng</target>
   <demandValue> 10.313549 </demandValue>
  </demand>
  <demand id="STTLng_CHINng">
   <source>STTLng</source>
   <target>CHINng</target>
   <demandValue> 43.784091 </demandValue>
  </demand>
  <demand id="STTLng_DNVRng">
   <source>STTLng</source>
   <target>DNVRng</target>
   <demandValue> 6.213755 </demandValue>
  </demand>
  <demand id="STTLng_HSTNng">
   <source>STTLng</source>
   <target>HSTNng</target>
   <demandValue> 4.489877 </demandValue>
  </demand>
  <demand id="STTLng_IPLSng">
   <source>STTLng</source>
   <target>IPLSng</target>
   <demandValue> 28.523835 </demandValue>
  </demand>
  <demand id="STTLng_KSCYng">
   <source>STTLng</source>
   <target>KSCYng</target>
   <demandValue> 6.376243 </demandValue>
  </demand>
  <demand id="STTLng_LOSAng">
   <source>STTLng</source>
   <target>LOSAng</target>
   <demandValue> 39.779208 </demandValue>
  </demand>
  <demand id="STTLng_NYCMng">
   <source>STTLng</source>
   <target>NYCMng</target>
   <demandValue> 17.880691 </demandValue>
  </demand>
  <demand id="STTLng_SNVAng">
   <source>STTLng</source>
   <target>SNVAng</target>
   <demandValue> 9.385141 </demandValue>
  </demand>
  <demand id="STTLng_WASHng">
   <source>STTLng</source>
   <target>WASHng</target>
   <demandValue> 18.562621 </demandValue>
  </demand>
  <demand id="WASHng_ATLAM5">
   <source>WASHng</source>
   <target>ATLAM5</target>
   <demandValue> 1.531013 </demandValue>
  </demand>
  <demand id="WASHng_ATLAng">
   <source>WASHng</source>
   <target>ATLAng</target>
   <demandValue> 119.978837 </demandValue>
  </demand>
  <demand id="WASHng_CHINng">
   <source>WASHng</source>
   <target>CHINng</target>
   <demandValue> 91.947117 </demandValue>
  </demand>
  <demand id="WASHng_DNVRng">
   <source>WASHng</source>
   <target>DNVRng</target>
   <demandValue> 79.023736 </demandValue>
  </demand>
  <demand id="WASHng_HSTNng">
   <source>WASHng</source>
   <target>HSTNng</target>
   <demandValue> 20.327723 </demandValue>
  </demand>
  <demand id="WASHng_IPLSng">
   <source>WASHng</source>
   <target>IPLSng</target>
   <demandValue> 25.030227 </demandValue>
  </demand>
  <demand id="WASHng_KSCYng">
   <source>WASHng</source>
   <target>KSCYng</target>
   <demandValue> 28.575704 </demandValue>
  </demand>
  <demand id="WASHng_LOSAng">
   <source>WASHng</source>
   <target>LOSAng</target>
   <demandValue> 114.315000 </demandValue>
  </demand>
  <demand id="WASHng_NYCMng">
   <source>WASHng</source>
   <target>NYCMng</target>
   <demandValue> 221.571507 </demandValue>
  </demand>
  <demand id="WASHng_SNVAng">
   <source>WASHng</source>
   <target>SNVAng</target>
   <demandValue> 10.250640 </demandValue>
  </demand>
  <demand id="WASHng_STTLng">
   <source>WASHng</source>
   <target>STTLng</target>
   <demandValue> 60.095744 </demandValue>
  </demand>
 </demands>
</network>