<?xml version="1.0"?>
<network xmlns="http://sndlib.zib.de/network" version="1.0">
 <meta>
  <granularity>5min</granularity>
  <time>20040310-0910</time>
  <unit>MBITPERSEC</unit>
  <origin>Yin Zhang, http://userweb.cs.utexas.edu/~yzhang/research/AbileneTM/</origin>
 </meta>
 <networkStructure>
  <nodes coordinatesType="geographical">
   <node id="ATLAM5">
    <coordinates>
     <x>-84.383300</x>
     <y>33.750000</y>
    </coordinates>
   </node>
   <node id="ATLAng">
    <coordinates>
     <x>-85.5</x>
     <y>34.5</y>
    </coordinates>
   </node>
   <node id="CHINng">
    <coordinates>
     <x>-87.616700</x>
     <y>41.833300</y>
    </coordinates>
   </node>
   <node id="DNVRng">
    <coordinates>
     <x>-105.000000</x>
     <y>40.750000</y>
    </coordinates>
   </node>
   <node id="HSTNng">
    <coordinates>
     <x>-95.517364</x>
     <y>29.770031</y>
    </coordinates>
   </node>
   <node id="IPLSng">
    <coordinates>
     <x>-86.159535</x>
     <y>39.780622</y>
    </coordinates>
   </node>
   <node id="KSCYng">
    <coordinates>
     <x>-96.596704</x>
     <y>38.961694</y>
    </coordinates>
   </node>
   <node id="LOSAng">
    <coordinates>
     <x>-118.250000</x>
     <y>34.050000</y>
    </coordinates>
   </node>
   <node id="NYCMng">
    <coordinates>
     <x>-73.966700</x>
     <y>40.783300</y>
    </coordinates>
   </node>
   <node id="SNVAng">
    <coordinates>
     <x>-122.02553</x>
     <y>37.38575</y>
    </coordinates>
   </node>
   <node id="STTLng">
    <coordinates>
     <x>-122.300000</x>
     <y>47.600000</y>
    </coordinates>
   </node>
   <node id="WASHng">
    <coordinates>
     <x>-77.026842</x>
     <y>38.897303</y>
    </coordinates>
   </node>
  </nodes>
  <links>
  </links>
 </networkStructure>
 <demands>
  <demand id="ATLAM5_ATLAng">
   <source>ATLAM5</source>
   <target>ATLAng</target>
   <demandValue> 0.153005 </demandValue>
  </demand>
  <demand id="ATLAM5_CHINng">
   <source>ATLAM5</source>
   <target>CHINng</target>
   <demandValue> 0.515472 </demandValue>
  </demand>
  <demand id="ATLAM5_DNVRng">
   <source>ATLAM5</source>
   <target>DNVRng</target>
   <demandValue> 0.092821 </demandValue>
  </demand>
  <demand id="ATLAM5_HSTNng">
   <source>ATLAM5</source>
   <target>HSTNng</target>
   <demandValue> 0.338432 </demandValue>
  </demand>
  <demand id="ATLAM5_IPLSng">
   <source>ATLAM5</source>
   <target>IPLSng</target>
   <demandValue> 0.418077 </demandValue>
  </demand>
  <demand id="ATLAM5_KSCYng">
   <source>ATLAM5</source>
   <target>KSCYng</target>
   <demandValue> 0.425405 </demandValue>
  </demand>
  <demand id="ATLAM5_LOSAng">
   <source>ATLAM5</source>
   <target>LOSAng</target>
   <demandValue> 0.618587 </demandValue>
  </demand>
  <demand id="ATLAM5_NYCMng">
   <source>ATLAM5</source>
   <target>NYCMng</target>
   <demandValue> 0.364421 </demandValue>
  </demand>
  <demand id="ATLAM5_SNVAng">
   <source>ATLAM5</source>
   <target>SNVAng</target>
   <demandValue> 0.120648 </demandValue>
  </demand>
  <demand id="ATLAM5_STTLng">
   <source>ATLAM5</source>
   <target>STTLng</target>
   <demandValue> 0.147704 </demandValue>
  </demand>
  <demand id="ATLAM5_WASHng">
   <source>ATLAM5</source>
   <target>WASHng</target>
   <demandValue> 1.549920 </demandValue>
  </demand>
  <demand id="ATLAng_ATLAM5">
   <source>ATLAng</source>
   <target>ATLAM5</target>
   <demandValue> 0.026667 </demandValue>
  </demand>
  <demand id="ATLAng_CHINng">
   <source>ATLAng</source>
   <target>CHINng</target>
   <demandValue> 12.585320 </demandValue>
  </demand>
  <demand id="ATLAng_DNVRng">
   <source>ATLAng</source>
   <target>DNVRng</target>
   <demandValue> 5.356299 </demandValue>
  </demand>
  <demand id="ATLAng_HSTNng">
   <source>ATLAng</source>
   <target>HSTNng</target>
   <demandValue> 3.774693 </demandValue>
  </demand>
  <demand id="ATLAng_IPLSng">
   <source>ATLAng</source>
   <target>IPLSng</target>
   <demandValue> 24.096957 </demandValue>
  </demand>
  <demand id="ATLAng_KSCYng">
   <source>ATLAng</source>
   <target>KSCYng</target>
   <demandValue> 4.610528 </demandValue>
  </demand>
  <demand id="ATLAng_LOSAng">
   <source>ATLAng</source>
   <target>LOSAng</target>
   <demandValue> 12.330289 </demandValue>
  </demand>
  <demand id="ATLAng_NYCMng">
   <source>ATLAng</source>
   <target>NYCMng</target>
   <demandValue> 11.832661 </demandValue>
  </demand>
  <demand id="ATLAng_SNVAng">
   <source>ATLAng</source>
   <target>SNVAng</target>
   <demandValue> 0.909329 </demandValue>
  </demand>
  <demand id="ATLAng_STTLng">
   <source>ATLAng</source>
   <target>STTLng</target>
   <demandValue> 11.454797 </demandValue>
  </demand>
  <demand id="ATLAng_WASHng">
   <source>ATLAng</source>
   <target>WASHng</target>
   <demandValue> 58.163571 </demandValue>
  </demand>
  <demand id="CHINng_ATLAM5">
   <source>CHINng</source>
   <target>ATLAM5</target>
   <demandValue> 1.271235 </demandValue>
  </demand>
  <demand id="CHINng_ATLAng">
   <source>CHINng</source>
   <target>ATLAng</target>
   <demandValue> 16.841149 </demandValue>
  </demand>
  <demand id="CHINng_DNVRng">
   <source>CHINng</source>
   <target>DNVRng</target>
   <demandValue> 19.842059 </demandValue>
  </demand>
  <demand id="CHINng_HSTNng">
   <source>CHINng</source>
   <target>HSTNng</target>
   <demandValue> 14.960757 </demandValue>
  </demand>
  <demand id="CHINng_IPLSng">
   <source>CHINng</source>
   <target>IPLSng</target>
   <demandValue> 55.844563 </demandValue>
  </demand>
  <demand id="CHINng_KSCYng">
   <source>CHINng</source>
   <target>KSCYng</target>
   <demandValue> 19.312621 </demandValue>
  </demand>
  <demand id="CHINng_LOSAng">
   <source>CHINng</source>
   <target>LOSAng</target>
   <demandValue> 54.218637 </demandValue>
  </demand>
  <demand id="CHINng_NYCMng">
   <source>CHINng</source>
   <target>NYCMng</target>
   <demandValue> 24.495843 </demandValue>
  </demand>
  <demand id="CHINng_SNVAng">
   <source>CHINng</source>
   <target>SNVAng</target>
   <demandValue> 9.890765 </demandValue>
  </demand>
  <demand id="CHINng_STTLng">
   <source>CHINng</source>
   <target>STTLng</target>
   <demandValue> 17.337464 </demandValue>
  </demand>
  <demand id="CHINng_WASHng">
   <source>CHINng</source>
   <target>WASHng</target>
   <demandValue> 32.780480 </demandValue>
  </demand>
  <demand id="DNVRng_ATLAM5">
   <source>DNVRng</source>
   <target>ATLAM5</target>
   <demandValue> 0.192917 </demandValue>
  </demand>
  <demand id="DNVRng_ATLAng">
   <source>DNVRng</source>
   <target>ATLAng</target>
   <demandValue> 5.156821 </demandValue>
  </demand>
  <demand id="DNVRng_CHINng">
   <source>DNVRng</source>
   <target>CHINng</target>
   <demandValue> 87.939864 </demandValue>
  </demand>
  <demand id="DNVRng_HSTNng">
   <source>DNVRng</source>
   <target>HSTNng</target>
   <demandValue> 22.430533 </demandValue>
  </demand>
  <demand id="DNVRng_IPLSng">
   <source>DNVRng</source>
   <target>IPLSng</target>
   <demandValue> 29.279488 </demandValue>
  </demand>
  <demand id="DNVRng_KSCYng">
   <source>DNVRng</source>
   <target>KSCYng</target>
   <demandValue> 18.837851 </demandValue>
  </demand>
  <demand id="DNVRng_LOSAng">
   <source>DNVRng</source>
   <target>LOSAng</target>
   <demandValue> 13.874091 </demandValue>
  </demand>
  <demand id="DNVRng_NYCMng">
   <source>DNVRng</source>
   <target>NYCMng</target>
   <demandValue> 22.749843 </demandValue>
  </demand>
  <demand id="DNVRng_SNVAng">
   <source>DNVRng</source>
   <target>SNVAng</target>
   <demandValue> 8.077957 </demandValue>
  </demand>
  <demand id="DNVRng_STTLng">
   <source>DNVRng</source>
   <target>STTLng</target>
   <demandValue> 13.386301 </demandValue>
  </demand>
  <demand id="DNVRng_WASHng">
   <source>DNVRng</source>
   <target>WASHng</target>
   <demandValue> 77.945659 </demandValue>
  </demand>
  <demand id="HSTNng_ATLAM5">
   <source>HSTNng</source>
   <target>ATLAM5</target>
   <demandValue> 2.317320 </demandValue>
  </demand>
  <demand id="HSTNng_ATLAng">
   <source>HSTNng</source>
   <target>ATLAng</target>
   <demandValue> 2.668555 </demandValue>
  </demand>
  <demand id="HSTNng_CHINng">
   <source>HSTNng</source>
   <target>CHINng</target>
   <demandValue> 57.167752 </demandValue>
  </demand>
  <demand id="HSTNng_DNVRng">
   <source>HSTNng</source>
   <target>DNVRng</target>
   <demandValue> 3.821291 </demandValue>
  </demand>
  <demand id="HSTNng_IPLSng">
   <source>HSTNng</source>
   <target>IPLSng</target>
   <demandValue> 13.492117 </demandValue>
  </demand>
  <demand id="HSTNng_KSCYng">
   <source>HSTNng</source>
   <target>KSCYng</target>
   <demandValue> 5.271944 </demandValue>
  </demand>
  <demand id="HSTNng_LOSAng">
   <source>HSTNng</source>
   <target>LOSAng</target>
   <demandValue> 101.077272 </demandValue>
  </demand>
  <demand id="HSTNng_NYCMng">
   <source>HSTNng</source>
   <target>NYCMng</target>
   <demandValue> 5.288835 </demandValue>
  </demand>
  <demand id="HSTNng_SNVAng">
   <source>HSTNng</source>
   <target>SNVAng</target>
   <demandValue> 3.292053 </demandValue>
  </demand>
  <demand id="HSTNng_STTLng">
   <source>HSTNng</source>
   <target>STTLng</target>
   <demandValue> 5.167728 </demandValue>
  </demand>
  <demand id="HSTNng_WASHng">
   <source>HSTNng</source>
   <target>WASHng</target>
   <demandValue> 7.977227 </demandValue>
  </demand>
  <demand id="IPLSng_ATLAM5">
   <source>IPLSng</source>
   <target>ATLAM5</target>
   <demandValue> 0.741115 </demandValue>
  </demand>
  <demand id="IPLSng_ATLAng">
   <source>IPLSng</source>
   <target>ATLAng</target>
   <demandValue> 12.087592 </demandValue>
  </demand>
  <demand id="IPLSng_CHINng">
   <source>IPLSng</source>
   <target>CHINng</target>
   <demandValue> 127.464829 </demandValue>
  </demand>
  <demand id="IPLSng_DNVRng">
   <source>IPLSng</source>
   <target>DNVRng</target>
   <demandValue> 17.459640 </demandValue>
  </demand>
  <demand id="IPLSng_HSTNng">
   <source>IPLSng</source>
   <target>HSTNng</target>
   <demandValue> 10.151893 </demandValue>
  </demand>
  <demand id="IPLSng_KSCYng">
   <source>IPLSng</source>
   <target>KSCYng</target>
   <demandValue> 17.683747 </demandValue>
  </demand>
  <demand id="IPLSng_LOSAng">
   <source>IPLSng</source>
   <target>LOSAng</target>
   <demandValue> 23.038888 </demandValue>
  </demand>
  <demand id="IPLSng_NYCMng">
   <source>IPLSng</source>
   <target>NYCMng</target>
   <demandValue> 43.586275 </demandValue>
  </demand>
  <demand id="IPLSng_SNVAng">
   <source>IPLSng</source>
   <target>SNVAng</target>
   <demandValue> 9.581435 </demandValue>
  </demand>
  <demand id="IPLSng_STTLng">
   <source>IPLSng</source>
   <target>STTLng</target>
   <demandValue> 15.203808 </demandValue>
  </demand>
  <demand id="IPLSng_WASHng">
   <source>IPLSng</source>
   <target>WASHng</target>
   <demandValue> 27.436912 </demandValue>
  </demand>
  <demand id="KSCYng_ATLAM5">
   <source>KSCYng</source>
   <target>ATLAM5</target>
   <demandValue> 0.420560 </demandValue>
  </demand>
  <demand id="KSCYng_ATLAng">
   <source>KSCYng</source>
   <target>ATLAng</target>
   <demandValue> 4.104155 </demandValue>
  </demand>
  <demand id="KSCYng_CHINng">
   <source>KSCYng</source>
   <target>CHINng</target>
   <demandValue> 41.394064 </demandValue>
  </demand>
  <demand id="KSCYng_DNVRng">
   <source>KSCYng</source>
   <target>DNVRng</target>
   <demandValue> 7.765560 </demandValue>
  </demand>
  <demand id="KSCYng_HSTNng">
   <source>KSCYng</source>
   <target>HSTNng</target>
   <demandValue> 3.212019 </demandValue>
  </demand>
  <demand id="KSCYng_IPLSng">
   <source>KSCYng</source>
   <target>IPLSng</target>
   <demandValue> 10.605952 </demandValue>
  </demand>
  <demand id="KSCYng_LOSAng">
   <source>KSCYng</source>
   <target>LOSAng</target>
   <demandValue> 8.506387 </demandValue>
  </demand>
  <demand id="KSCYng_NYCMng">
   <source>KSCYng</source>
   <target>NYCMng</target>
   <demandValue> 9.192283 </demandValue>
  </demand>
  <demand id="KSCYng_SNVAng">
   <source>KSCYng</source>
   <target>SNVAng</target>
   <demandValue> 1.331429 </demandValue>
  </demand>
  <demand id="KSCYng_STTLng">
   <source>KSCYng</source>
   <target>STTLng</target>
   <demandValue> 5.699291 </demandValue>
  </demand>
  <demand id="KSCYng_WASHng">
   <source>KSCYng</source>
   <target>WASHng</target>
   <demandValue> 8.230112 </demandValue>
  </demand>
  <demand id="LOSAng_ATLAM5">
   <source>LOSAng</source>
   <target>ATLAM5</target>
   <demandValue> 0.101376 </demandValue>
  </demand>
  <demand id="LOSAng_ATLAng">
   <source>LOSAng</source>
   <target>ATLAng</target>
   <demandValue> 9.553880 </demandValue>
  </demand>
  <demand id="LOSAng_CHINng">
   <source>LOSAng</source>
   <target>CHINng</target>
   <demandValue> 127.397099 </demandValue>
  </demand>
  <demand id="LOSAng_DNVRng">
   <source>LOSAng</source>
   <target>DNVRng</target>
   <demandValue> 8.090611 </demandValue>
  </demand>
  <demand id="LOSAng_HSTNng">
   <source>LOSAng</source>
   <target>HSTNng</target>
   <demandValue> 55.227931 </demandValue>
  </demand>
  <demand id="LOSAng_IPLSng">
   <source>LOSAng</source>
   <target>IPLSng</target>
   <demandValue> 26.559125 </demandValue>
  </demand>
  <demand id="LOSAng_KSCYng">
   <source>LOSAng</source>
   <target>KSCYng</target>
   <demandValue> 7.233093 </demandValue>
  </demand>
  <demand id="LOSAng_NYCMng">
   <source>LOSAng</source>
   <target>NYCMng</target>
   <demandValue> 39.634605 </demandValue>
  </demand>
  <demand id="LOSAng_SNVAng">
   <source>LOSAng</source>
   <target>SNVAng</target>
   <demandValue> 8.106467 </demandValue>
  </demand>
  <demand id="LOSAng_STTLng">
   <source>LOSAng</source>
   <target>STTLng</target>
   <demandValue> 32.459437 </demandValue>
  </demand>
  <demand id="LOSAng_WASHng">
   <source>LOSAng</source>
   <target>WASHng</target>
   <demandValue> 40.099243 </demandValue>
  </demand>
  <demand id="NYCMng_ATLAM5">
   <source>NYCMng</source>
   <target>ATLAM5</target>
   <demandValue> 1.034520 </demandValue>
  </demand>
  <demand id="NYCMng_ATLAng">
   <source>NYCMng</source>
   <target>ATLAng</target>
   <demandValue> 22.999437 </demandValue>
  </demand>
  <demand id="NYCMng_CHINng">
   <source>NYCMng</source>
   <target>CHINng</target>
   <demandValue> 59.562027 </demandValue>
  </demand>
  <demand id="NYCMng_DNVRng">
   <source>NYCMng</source>
   <target>DNVRng</target>
   <demandValue> 32.403043 </demandValue>
  </demand>
  <demand id="NYCMng_HSTNng">
   <source>NYCMng</source>
   <target>HSTNng</target>
   <demandValue> 33.879043 </demandValue>
  </demand>
  <demand id="NYCMng_IPLSng">
   <source>NYCMng</source>
   <target>IPLSng</target>
   <demandValue> 57.015715 </demandValue>
  </demand>
  <demand id="NYCMng_KSCYng">
   <source>NYCMng</source>
   <target>KSCYng</target>
   <demandValue> 24.371664 </demandValue>
  </demand>
  <demand id="NYCMng_LOSAng">
   <source>NYCMng</source>
   <target>LOSAng</target>
   <demandValue> 77.169427 </demandValue>
  </demand>
  <demand id="NYCMng_SNVAng">
   <source>NYCMng</source>
   <target>SNVAng</target>
   <demandValue> 10.782736 </demandValue>
  </demand>
  <demand id="NYCMng_STTLng">
   <source>NYCMng</source>
   <target>STTLng</target>
   <demandValue> 49.398184 </demandValue>
  </demand>
  <demand id="NYCMng_WASHng">
   <source>NYCMng</source>
   <target>WASHng</target>
   <demandValue> 107.698541 </demandValue>
  </demand>
  <demand id="SNVAng_ATLAng">
   <source>SNVAng</source>
   <target>ATLAng</target>
   <demandValue> 0.418091 </demandValue>
  </demand>
  <demand id="SNVAng_CHINng">
   <source>SNVAng</source>
   <target>CHINng</target>
   <demandValue> 4.303171 </demandValue>
  </demand>
  <demand id="SNVAng_DNVRng">
   <source>SNVAng</source>
   <target>DNVRng</target>
   <demandValue> 2.941613 </demandValue>
  </demand>
  <demand id="SNVAng_HSTNng">
   <source>SNVAng</source>
   <target>HSTNng</target>
   <demandValue> 1.144995 </demandValue>
  </demand>
  <demand id="SNVAng_IPLSng">
   <source>SNVAng</source>
   <target>IPLSng</target>
   <demandValue> 0.963248 </demandValue>
  </demand>
  <demand id="SNVAng_KSCYng">
   <source>SNVAng</source>
   <target>KSCYng</target>
   <demandValue> 0.494829 </demandValue>
  </demand>
  <demand id="SNVAng_LOSAng">
   <source>SNVAng</source>
   <target>LOSAng</target>
   <demandValue> 29.782395 </demandValue>
  </demand>
  <demand id="SNVAng_NYCMng">
   <source>SNVAng</source>
   <target>NYCMng</target>
   <demandValue> 1.301453 </demandValue>
  </demand>
  <demand id="SNVAng_STTLng">
   <source>SNVAng</source>
   <target>STTLng</target>
   <demandValue> 53.984093 </demandValue>
  </demand>
  <demand id="SNVAng_WASHng">
   <source>SNVAng</source>
   <target>WASHng</target>
   <demandValue> 0.739699 </demandValue>
  </demand>
  <demand id="STTLng_ATLAM5">
   <source>STTLng</source>
   <target>ATLAM5</target>
   <demandValue> 0.044381 </demandValue>
  </demand>
  <demand id="STTLng_ATLAng">
   <source>STTLng</source>
   <target>ATLAng</target>
   <demandValue> 6.920981 </demandValue>
  </demand>
  <demand id="STTLng_CHINng">
   <source>STTLng</source>
   <target>CHINng</target>
   <demandValue> 61.823187 </demandValue>
  </demand>
  <demand id="STTLng_DNVRng">
   <source>STTLng</source>
   <target>DNVRng</target>
   <demandValue> 9.877485 </demandValue>
  </demand>
  <demand id="STTLng_HSTNng">
   <source>STTLng</source>
   <target>HSTNng</target>
   <demandValue> 5.238920 </demandValue>
  </demand>
  <demand id="STTLng_IPLSng">
   <source>STTLng</source>
   <target>IPLSng</target>
   <demandValue> 10.899701 </demandValue>
  </demand>
  <demand id="STTLng_KSCYng">
   <source>STTLng</source>
   <target>KSCYng</target>
   <demandValue> 4.246992 </demandValue>
  </demand>
  <demand id="STTLng_LOSAng">
   <source>STTLng</source>
   <target>LOSAng</target>
   <demandValue> 32.135557 </demandValue>
  </demand>
  <demand id="STTLng_NYCMng">
   <source>STTLng</source>
   <target>NYCMng</target>
   <demandValue> 16.492045 </demandValue>
  </demand>
  <demand id="STTLng_SNVAng">
   <source>STTLng</source>
   <target>SNVAng</target>
   <demandValue> 7.888187 </demandValue>
  </demand>
  <demand id="STTLng_WASHng">
   <source>STTLng</source>
   <target>WASHng</target>
   <demandValue> 7.294619 </demandValue>
  </demand>
  <demand id="WASHng_ATLAM5">
   <source>WASHng</source>
   <target>ATLAM5</target>
   <demandValue> 3.429949 </demandValue>
  </demand>
  <demand id="WASHng_ATLAng">
   <source>WASHng</source>
   <target>ATLAng</target>
   <demandValue> 102.751811 </demandValue>
  </demand>
  <demand id="WASHng_CHINng">
   <source>WASHng</source>
   <target>CHINng</target>
   <demandValue> 72.478637 </demandValue>
  </demand>
  <demand id="WASHng_DNVRng">
   <source>WASHng</source>
   <target>DNVRng</target>
   <demandValue> 69.706672 </demandValue>
  </demand>
  <demand id="WASHng_HSTNng">
   <source>WASHng</source>
   <target>HSTNng</target>
   <demandValue> 30.835061 </demandValue>
  </demand>
  <demand id="WASHng_IPLSng">
   <source>WASHng</source>
   <target>IPLSng</target>
   <demandValue> 58.092923 </demandValue>
  </demand>
  <demand id="WASHng_KSCYng">
   <source>WASHng</source>
   <target>KSCYng</target>
   <demandValue> 20.614669 </demandValue>
  </demand>
  <demand id="WASHng_LOSAng">
   <source>WASHng</source>
   <target>LOSAng</target>
   <demandValue> 75.342259 </demandValue>
  </demand>
  <demand id="WASHng_NYCMng">
   <source>WASHng</source>
   <target>NYCMng</target>
   <demandValue> 182.702059 </demandValue>
  </demand>
  <demand id="WASHng_SNVAng">
   <source>WASHng</source>
   <target>SNVAng</target>
   <demandValue> 6.384539 </demandValue>
  </demand>
  <demand id="WASHng_STTLng">
   <source>WASHng</source>
   <target>STTLng</target>
   <demandValue> 46.745544 </demandValue>
  </demand>
 </demands>
</network>