<?xml version="1.0"?>
<network xmlns="http://sndlib.zib.de/network" version="1.0">
 <meta>
  <granularity>5min</granularity>
  <time>20040303-2345</time>
  <unit>MBITPERSEC</unit>
  <origin>Yin Zhang, http://userweb.cs.utexas.edu/~yzhang/research/AbileneTM/</origin>
 </meta>
 <networkStructure>
  <nodes coordinatesType="geographical">
   <node id="ATLAM5">
    <coordinates>
     <x>-84.383300</x>
     <y>33.750000</y>
    </coordinates>
   </node>
   <node id="ATLAng">
    <coordinates>
     <x>-85.5</x>
     <y>34.5</y>
    </coordinates>
   </node>
   <node id="CHINng">
    <coordinates>
     <x>-87.616700</x>
     <y>41.833300</y>
    </coordinates>
   </node>
   <node id="DNVRng">
    <coordinates>
     <x>-105.000000</x>
     <y>40.750000</y>
    </coordinates>
   </node>
   <node id="HSTNng">
    <coordinates>
     <x>-95.517364</x>
     <y>29.770031</y>
    </coordinates>
   </node>
   <node id="IPLSng">
    <coordinates>
     <x>-86.159535</x>
     <y>39.780622</y>
    </coordinates>
   </node>
   <node id="KSCYng">
    <coordinates>
     <x>-96.596704</x>
     <y>38.961694</y>
    </coordinates>
   </node>
   <node id="LOSAng">
    <coordinates>
     <x>-118.250000</x>
     <y>34.050000</y>
    </coordinates>
   </node>
   <node id="NYCMng">
    <coordinates>
     <x>-73.966700</x>
     <y>40.783300</y>
    </coordinates>
   </node>
   <node id="SNVAng">
    <coordinates>
     <x>-122.02553</x>
     <y>37.38575</y>
    </coordinates>
   </node>
   <node id="STTLng">
    <coordinates>
     <x>-122.300000</x>
     <y>47.600000</y>
    </coordinates>
   </node>
   <node id="WASHng">
    <coordinates>
     <x>-77.026842</x>
     <y>38.897303</y>
    </coordinates>
   </node>
  </nodes>
  <links>
  </links>
 </networkStructure>
 <demands>
  <demand id="ATLAM5_ATLAng">
   <source>ATLAM5</source>
   <target>ATLAng</target>
   <demandValue> 0.921445 </demandValue>
  </demand>
  <demand id="ATLAM5_CHINng">
   <source>ATLAM5</source>
   <target>CHINng</target>
   <demandValue> 0.908491 </demandValue>
  </demand>
  <demand id="ATLAM5_DNVRng">
   <source>ATLAM5</source>
   <target>DNVRng</target>
   <demandValue> 0.262728 </demandValue>
  </demand>
  <demand id="ATLAM5_HSTNng">
   <source>ATLAM5</source>
   <target>HSTNng</target>
   <demandValue> 0.744909 </demandValue>
  </demand>
  <demand id="ATLAM5_IPLSng">
   <source>ATLAM5</source>
   <target>IPLSng</target>
   <demandValue> 0.768157 </demandValue>
  </demand>
  <demand id="ATLAM5_KSCYng">
   <source>ATLAM5</source>
   <target>KSCYng</target>
   <demandValue> 1.413672 </demandValue>
  </demand>
  <demand id="ATLAM5_LOSAng">
   <source>ATLAM5</source>
   <target>LOSAng</target>
   <demandValue> 0.693021 </demandValue>
  </demand>
  <demand id="ATLAM5_NYCMng">
   <source>ATLAM5</source>
   <target>NYCMng</target>
   <demandValue> 1.706581 </demandValue>
  </demand>
  <demand id="ATLAM5_SNVAng">
   <source>ATLAM5</source>
   <target>SNVAng</target>
   <demandValue> 0.179851 </demandValue>
  </demand>
  <demand id="ATLAM5_STTLng">
   <source>ATLAM5</source>
   <target>STTLng</target>
   <demandValue> 0.060747 </demandValue>
  </demand>
  <demand id="ATLAM5_WASHng">
   <source>ATLAM5</source>
   <target>WASHng</target>
   <demandValue> 1.782949 </demandValue>
  </demand>
  <demand id="ATLAng_ATLAM5">
   <source>ATLAng</source>
   <target>ATLAM5</target>
   <demandValue> 4.556400 </demandValue>
  </demand>
  <demand id="ATLAng_CHINng">
   <source>ATLAng</source>
   <target>CHINng</target>
   <demandValue> 20.023259 </demandValue>
  </demand>
  <demand id="ATLAng_DNVRng">
   <source>ATLAng</source>
   <target>DNVRng</target>
   <demandValue> 12.964096 </demandValue>
  </demand>
  <demand id="ATLAng_HSTNng">
   <source>ATLAng</source>
   <target>HSTNng</target>
   <demandValue> 10.861893 </demandValue>
  </demand>
  <demand id="ATLAng_IPLSng">
   <source>ATLAng</source>
   <target>IPLSng</target>
   <demandValue> 65.558395 </demandValue>
  </demand>
  <demand id="ATLAng_KSCYng">
   <source>ATLAng</source>
   <target>KSCYng</target>
   <demandValue> 5.903752 </demandValue>
  </demand>
  <demand id="ATLAng_LOSAng">
   <source>ATLAng</source>
   <target>LOSAng</target>
   <demandValue> 22.989801 </demandValue>
  </demand>
  <demand id="ATLAng_NYCMng">
   <source>ATLAng</source>
   <target>NYCMng</target>
   <demandValue> 27.550008 </demandValue>
  </demand>
  <demand id="ATLAng_SNVAng">
   <source>ATLAng</source>
   <target>SNVAng</target>
   <demandValue> 2.325897 </demandValue>
  </demand>
  <demand id="ATLAng_STTLng">
   <source>ATLAng</source>
   <target>STTLng</target>
   <demandValue> 9.473581 </demandValue>
  </demand>
  <demand id="ATLAng_WASHng">
   <source>ATLAng</source>
   <target>WASHng</target>
   <demandValue> 68.228467 </demandValue>
  </demand>
  <demand id="CHINng_ATLAM5">
   <source>CHINng</source>
   <target>ATLAM5</target>
   <demandValue> 1.467035 </demandValue>
  </demand>
  <demand id="CHINng_ATLAng">
   <source>CHINng</source>
   <target>ATLAng</target>
   <demandValue> 25.206624 </demandValue>
  </demand>
  <demand id="CHINng_DNVRng">
   <source>CHINng</source>
   <target>DNVRng</target>
   <demandValue> 17.836405 </demandValue>
  </demand>
  <demand id="CHINng_HSTNng">
   <source>CHINng</source>
   <target>HSTNng</target>
   <demandValue> 22.623573 </demandValue>
  </demand>
  <demand id="CHINng_IPLSng">
   <source>CHINng</source>
   <target>IPLSng</target>
   <demandValue> 45.144232 </demandValue>
  </demand>
  <demand id="CHINng_KSCYng">
   <source>CHINng</source>
   <target>KSCYng</target>
   <demandValue> 17.632403 </demandValue>
  </demand>
  <demand id="CHINng_LOSAng">
   <source>CHINng</source>
   <target>LOSAng</target>
   <demandValue> 42.235989 </demandValue>
  </demand>
  <demand id="CHINng_NYCMng">
   <source>CHINng</source>
   <target>NYCMng</target>
   <demandValue> 8.600165 </demandValue>
  </demand>
  <demand id="CHINng_SNVAng">
   <source>CHINng</source>
   <target>SNVAng</target>
   <demandValue> 2.962371 </demandValue>
  </demand>
  <demand id="CHINng_STTLng">
   <source>CHINng</source>
   <target>STTLng</target>
   <demandValue> 20.321683 </demandValue>
  </demand>
  <demand id="CHINng_WASHng">
   <source>CHINng</source>
   <target>WASHng</target>
   <demandValue> 10.640283 </demandValue>
  </demand>
  <demand id="DNVRng_ATLAM5">
   <source>DNVRng</source>
   <target>ATLAM5</target>
   <demandValue> 0.295027 </demandValue>
  </demand>
  <demand id="DNVRng_ATLAng">
   <source>DNVRng</source>
   <target>ATLAng</target>
   <demandValue> 22.031240 </demandValue>
  </demand>
  <demand id="DNVRng_CHINng">
   <source>DNVRng</source>
   <target>CHINng</target>
   <demandValue> 59.803363 </demandValue>
  </demand>
  <demand id="DNVRng_HSTNng">
   <source>DNVRng</source>
   <target>HSTNng</target>
   <demandValue> 15.344115 </demandValue>
  </demand>
  <demand id="DNVRng_IPLSng">
   <source>DNVRng</source>
   <target>IPLSng</target>
   <demandValue> 37.429811 </demandValue>
  </demand>
  <demand id="DNVRng_KSCYng">
   <source>DNVRng</source>
   <target>KSCYng</target>
   <demandValue> 17.558707 </demandValue>
  </demand>
  <demand id="DNVRng_LOSAng">
   <source>DNVRng</source>
   <target>LOSAng</target>
   <demandValue> 32.322461 </demandValue>
  </demand>
  <demand id="DNVRng_NYCMng">
   <source>DNVRng</source>
   <target>NYCMng</target>
   <demandValue> 28.414381 </demandValue>
  </demand>
  <demand id="DNVRng_SNVAng">
   <source>DNVRng</source>
   <target>SNVAng</target>
   <demandValue> 11.372539 </demandValue>
  </demand>
  <demand id="DNVRng_STTLng">
   <source>DNVRng</source>
   <target>STTLng</target>
   <demandValue> 20.651112 </demandValue>
  </demand>
  <demand id="DNVRng_WASHng">
   <source>DNVRng</source>
   <target>WASHng</target>
   <demandValue> 57.988723 </demandValue>
  </demand>
  <demand id="HSTNng_ATLAM5">
   <source>HSTNng</source>
   <target>ATLAM5</target>
   <demandValue> 0.510069 </demandValue>
  </demand>
  <demand id="HSTNng_ATLAng">
   <source>HSTNng</source>
   <target>ATLAng</target>
   <demandValue> 5.368173 </demandValue>
  </demand>
  <demand id="HSTNng_CHINng">
   <source>HSTNng</source>
   <target>CHINng</target>
   <demandValue> 41.227443 </demandValue>
  </demand>
  <demand id="HSTNng_DNVRng">
   <source>HSTNng</source>
   <target>DNVRng</target>
   <demandValue> 11.532291 </demandValue>
  </demand>
  <demand id="HSTNng_IPLSng">
   <source>HSTNng</source>
   <target>IPLSng</target>
   <demandValue> 18.513781 </demandValue>
  </demand>
  <demand id="HSTNng_KSCYng">
   <source>HSTNng</source>
   <target>KSCYng</target>
   <demandValue> 4.706083 </demandValue>
  </demand>
  <demand id="HSTNng_LOSAng">
   <source>HSTNng</source>
   <target>LOSAng</target>
   <demandValue> 66.081219 </demandValue>
  </demand>
  <demand id="HSTNng_NYCMng">
   <source>HSTNng</source>
   <target>NYCMng</target>
   <demandValue> 25.430773 </demandValue>
  </demand>
  <demand id="HSTNng_SNVAng">
   <source>HSTNng</source>
   <target>SNVAng</target>
   <demandValue> 3.131821 </demandValue>
  </demand>
  <demand id="HSTNng_STTLng">
   <source>HSTNng</source>
   <target>STTLng</target>
   <demandValue> 4.475467 </demandValue>
  </demand>
  <demand id="HSTNng_WASHng">
   <source>HSTNng</source>
   <target>WASHng</target>
   <demandValue> 17.097728 </demandValue>
  </demand>
  <demand id="IPLSng_ATLAM5">
   <source>IPLSng</source>
   <target>ATLAM5</target>
   <demandValue> 0.610925 </demandValue>
  </demand>
  <demand id="IPLSng_ATLAng">
   <source>IPLSng</source>
   <target>ATLAng</target>
   <demandValue> 56.167963 </demandValue>
  </demand>
  <demand id="IPLSng_CHINng">
   <source>IPLSng</source>
   <target>CHINng</target>
   <demandValue> 197.203581 </demandValue>
  </demand>
  <demand id="IPLSng_DNVRng">
   <source>IPLSng</source>
   <target>DNVRng</target>
   <demandValue> 24.931376 </demandValue>
  </demand>
  <demand id="IPLSng_HSTNng">
   <source>IPLSng</source>
   <target>HSTNng</target>
   <demandValue> 14.586208 </demandValue>
  </demand>
  <demand id="IPLSng_KSCYng">
   <source>IPLSng</source>
   <target>KSCYng</target>
   <demandValue> 12.138429 </demandValue>
  </demand>
  <demand id="IPLSng_LOSAng">
   <source>IPLSng</source>
   <target>LOSAng</target>
   <demandValue> 33.397619 </demandValue>
  </demand>
  <demand id="IPLSng_NYCMng">
   <source>IPLSng</source>
   <target>NYCMng</target>
   <demandValue> 30.429272 </demandValue>
  </demand>
  <demand id="IPLSng_SNVAng">
   <source>IPLSng</source>
   <target>SNVAng</target>
   <demandValue> 8.128251 </demandValue>
  </demand>
  <demand id="IPLSng_STTLng">
   <source>IPLSng</source>
   <target>STTLng</target>
   <demandValue> 11.876112 </demandValue>
  </demand>
  <demand id="IPLSng_WASHng">
   <source>IPLSng</source>
   <target>WASHng</target>
   <demandValue> 41.292555 </demandValue>
  </demand>
  <demand id="KSCYng_ATLAM5">
   <source>KSCYng</source>
   <target>ATLAM5</target>
   <demandValue> 0.916072 </demandValue>
  </demand>
  <demand id="KSCYng_ATLAng">
   <source>KSCYng</source>
   <target>ATLAng</target>
   <demandValue> 6.173293 </demandValue>
  </demand>
  <demand id="KSCYng_CHINng">
   <source>KSCYng</source>
   <target>CHINng</target>
   <demandValue> 36.723125 </demandValue>
  </demand>
  <demand id="KSCYng_DNVRng">
   <source>KSCYng</source>
   <target>DNVRng</target>
   <demandValue> 17.603568 </demandValue>
  </demand>
  <demand id="KSCYng_HSTNng">
   <source>KSCYng</source>
   <target>HSTNng</target>
   <demandValue> 7.043669 </demandValue>
  </demand>
  <demand id="KSCYng_IPLSng">
   <source>KSCYng</source>
   <target>IPLSng</target>
   <demandValue> 14.975907 </demandValue>
  </demand>
  <demand id="KSCYng_LOSAng">
   <source>KSCYng</source>
   <target>LOSAng</target>
   <demandValue> 5.728459 </demandValue>
  </demand>
  <demand id="KSCYng_NYCMng">
   <source>KSCYng</source>
   <target>NYCMng</target>
   <demandValue> 19.020253 </demandValue>
  </demand>
  <demand id="KSCYng_SNVAng">
   <source>KSCYng</source>
   <target>SNVAng</target>
   <demandValue> 5.107147 </demandValue>
  </demand>
  <demand id="KSCYng_STTLng">
   <source>KSCYng</source>
   <target>STTLng</target>
   <demandValue> 5.515715 </demandValue>
  </demand>
  <demand id="KSCYng_WASHng">
   <source>KSCYng</source>
   <target>WASHng</target>
   <demandValue> 17.222621 </demandValue>
  </demand>
  <demand id="LOSAng_ATLAM5">
   <source>LOSAng</source>
   <target>ATLAM5</target>
   <demandValue> 0.579189 </demandValue>
  </demand>
  <demand id="LOSAng_ATLAng">
   <source>LOSAng</source>
   <target>ATLAng</target>
   <demandValue> 24.559301 </demandValue>
  </demand>
  <demand id="LOSAng_CHINng">
   <source>LOSAng</source>
   <target>CHINng</target>
   <demandValue> 96.739227 </demandValue>
  </demand>
  <demand id="LOSAng_DNVRng">
   <source>LOSAng</source>
   <target>DNVRng</target>
   <demandValue> 20.690224 </demandValue>
  </demand>
  <demand id="LOSAng_HSTNng">
   <source>LOSAng</source>
   <target>HSTNng</target>
   <demandValue> 18.206731 </demandValue>
  </demand>
  <demand id="LOSAng_IPLSng">
   <source>LOSAng</source>
   <target>IPLSng</target>
   <demandValue> 43.713443 </demandValue>
  </demand>
  <demand id="LOSAng_KSCYng">
   <source>LOSAng</source>
   <target>KSCYng</target>
   <demandValue> 8.622235 </demandValue>
  </demand>
  <demand id="LOSAng_NYCMng">
   <source>LOSAng</source>
   <target>NYCMng</target>
   <demandValue> 57.651995 </demandValue>
  </demand>
  <demand id="LOSAng_SNVAng">
   <source>LOSAng</source>
   <target>SNVAng</target>
   <demandValue> 31.202917 </demandValue>
  </demand>
  <demand id="LOSAng_STTLng">
   <source>LOSAng</source>
   <target>STTLng</target>
   <demandValue> 31.964179 </demandValue>
  </demand>
  <demand id="LOSAng_WASHng">
   <source>LOSAng</source>
   <target>WASHng</target>
   <demandValue> 142.290549 </demandValue>
  </demand>
  <demand id="NYCMng_ATLAM5">
   <source>NYCMng</source>
   <target>ATLAM5</target>
   <demandValue> 1.684803 </demandValue>
  </demand>
  <demand id="NYCMng_ATLAng">
   <source>NYCMng</source>
   <target>ATLAng</target>
   <demandValue> 62.877893 </demandValue>
  </demand>
  <demand id="NYCMng_CHINng">
   <source>NYCMng</source>
   <target>CHINng</target>
   <demandValue> 84.867307 </demandValue>
  </demand>
  <demand id="NYCMng_DNVRng">
   <source>NYCMng</source>
   <target>DNVRng</target>
   <demandValue> 49.686496 </demandValue>
  </demand>
  <demand id="NYCMng_HSTNng">
   <source>NYCMng</source>
   <target>HSTNng</target>
   <demandValue> 36.412413 </demandValue>
  </demand>
  <demand id="NYCMng_IPLSng">
   <source>NYCMng</source>
   <target>IPLSng</target>
   <demandValue> 108.527360 </demandValue>
  </demand>
  <demand id="NYCMng_KSCYng">
   <source>NYCMng</source>
   <target>KSCYng</target>
   <demandValue> 35.837648 </demandValue>
  </demand>
  <demand id="NYCMng_LOSAng">
   <source>NYCMng</source>
   <target>LOSAng</target>
   <demandValue> 90.422749 </demandValue>
  </demand>
  <demand id="NYCMng_SNVAng">
   <source>NYCMng</source>
   <target>SNVAng</target>
   <demandValue> 15.785403 </demandValue>
  </demand>
  <demand id="NYCMng_STTLng">
   <source>NYCMng</source>
   <target>STTLng</target>
   <demandValue> 48.300419 </demandValue>
  </demand>
  <demand id="NYCMng_WASHng">
   <source>NYCMng</source>
   <target>WASHng</target>
   <demandValue> 139.258229 </demandValue>
  </demand>
  <demand id="SNVAng_ATLAM5">
   <source>SNVAng</source>
   <target>ATLAM5</target>
   <demandValue> 0.074400 </demandValue>
  </demand>
  <demand id="SNVAng_ATLAng">
   <source>SNVAng</source>
   <target>ATLAng</target>
   <demandValue> 1.235587 </demandValue>
  </demand>
  <demand id="SNVAng_CHINng">
   <source>SNVAng</source>
   <target>CHINng</target>
   <demandValue> 6.430696 </demandValue>
  </demand>
  <demand id="SNVAng_DNVRng">
   <source>SNVAng</source>
   <target>DNVRng</target>
   <demandValue> 3.597475 </demandValue>
  </demand>
  <demand id="SNVAng_HSTNng">
   <source>SNVAng</source>
   <target>HSTNng</target>
   <demandValue> 1.765955 </demandValue>
  </demand>
  <demand id="SNVAng_IPLSng">
   <source>SNVAng</source>
   <target>IPLSng</target>
   <demandValue> 3.855381 </demandValue>
  </demand>
  <demand id="SNVAng_KSCYng">
   <source>SNVAng</source>
   <target>KSCYng</target>
   <demandValue> 0.918475 </demandValue>
  </demand>
  <demand id="SNVAng_LOSAng">
   <source>SNVAng</source>
   <target>LOSAng</target>
   <demandValue> 39.465539 </demandValue>
  </demand>
  <demand id="SNVAng_NYCMng">
   <source>SNVAng</source>
   <target>NYCMng</target>
   <demandValue> 1.947075 </demandValue>
  </demand>
  <demand id="SNVAng_STTLng">
   <source>SNVAng</source>
   <target>STTLng</target>
   <demandValue> 66.250493 </demandValue>
  </demand>
  <demand id="SNVAng_WASHng">
   <source>SNVAng</source>
   <target>WASHng</target>
   <demandValue> 3.011275 </demandValue>
  </demand>
  <demand id="STTLng_ATLAM5">
   <source>STTLng</source>
   <target>ATLAM5</target>
   <demandValue> 0.485152 </demandValue>
  </demand>
  <demand id="STTLng_ATLAng">
   <source>STTLng</source>
   <target>ATLAng</target>
   <demandValue> 11.136349 </demandValue>
  </demand>
  <demand id="STTLng_CHINng">
   <source>STTLng</source>
   <target>CHINng</target>
   <demandValue> 60.269525 </demandValue>
  </demand>
  <demand id="STTLng_DNVRng">
   <source>STTLng</source>
   <target>DNVRng</target>
   <demandValue> 8.114232 </demandValue>
  </demand>
  <demand id="STTLng_HSTNng">
   <source>STTLng</source>
   <target>HSTNng</target>
   <demandValue> 5.893861 </demandValue>
  </demand>
  <demand id="STTLng_IPLSng">
   <source>STTLng</source>
   <target>IPLSng</target>
   <demandValue> 20.173109 </demandValue>
  </demand>
  <demand id="STTLng_KSCYng">
   <source>STTLng</source>
   <target>KSCYng</target>
   <demandValue> 6.348403 </demandValue>
  </demand>
  <demand id="STTLng_LOSAng">
   <source>STTLng</source>
   <target>LOSAng</target>
   <demandValue> 33.506571 </demandValue>
  </demand>
  <demand id="STTLng_NYCMng">
   <source>STTLng</source>
   <target>NYCMng</target>
   <demandValue> 24.566968 </demandValue>
  </demand>
  <demand id="STTLng_SNVAng">
   <source>STTLng</source>
   <target>SNVAng</target>
   <demandValue> 15.880323 </demandValue>
  </demand>
  <demand id="STTLng_WASHng">
   <source>STTLng</source>
   <target>WASHng</target>
   <demandValue> 19.231397 </demandValue>
  </demand>
  <demand id="WASHng_ATLAM5">
   <source>WASHng</source>
   <target>ATLAM5</target>
   <demandValue> 2.133499 </demandValue>
  </demand>
  <demand id="WASHng_ATLAng">
   <source>WASHng</source>
   <target>ATLAng</target>
   <demandValue> 96.301493 </demandValue>
  </demand>
  <demand id="WASHng_CHINng">
   <source>WASHng</source>
   <target>CHINng</target>
   <demandValue> 109.241568 </demandValue>
  </demand>
  <demand id="WASHng_DNVRng">
   <source>WASHng</source>
   <target>DNVRng</target>
   <demandValue> 76.374872 </demandValue>
  </demand>
  <demand id="WASHng_HSTNng">
   <source>WASHng</source>
   <target>HSTNng</target>
   <demandValue> 47.508360 </demandValue>
  </demand>
  <demand id="WASHng_IPLSng">
   <source>WASHng</source>
   <target>IPLSng</target>
   <demandValue> 69.833552 </demandValue>
  </demand>
  <demand id="WASHng_KSCYng">
   <source>WASHng</source>
   <target>KSCYng</target>
   <demandValue> 23.332568 </demandValue>
  </demand>
  <demand id="WASHng_LOSAng">
   <source>WASHng</source>
   <target>LOSAng</target>
   <demandValue> 101.008531 </demandValue>
  </demand>
  <demand id="WASHng_NYCMng">
   <source>WASHng</source>
   <target>NYCMng</target>
   <demandValue> 189.453699 </demandValue>
  </demand>
  <demand id="WASHng_SNVAng">
   <source>WASHng</source>
   <target>SNVAng</target>
   <demandValue> 28.497875 </demandValue>
  </demand>
  <demand id="WASHng_STTLng">
   <source>WASHng</source>
   <target>STTLng</target>
   <demandValue> 46.764173 </demandValue>
  </demand>
 </demands>
</network>